src/__init__.py
src/uniqcharstest1/__init__.py
src/uniqcharstest1/main.py
src/uniqcharstest1/app/__init__.py
src/uniqcharstest1/app/app.py
src/uniqcharstest1/utils/__init__.py
src/uniqcharstest1/utils/exceptions.py
src/uniqcharstest1/utils/functions.py
tests/__init__.py
uniqcharstest1-1.0.dist-info/LICENSE
uniqcharstest1-1.0.dist-info/METADATA
uniqcharstest1-1.0.dist-info/WHEEL
uniqcharstest1-1.0.dist-info/entry_points.txt
uniqcharstest1-1.0.dist-info/top_level.txt
uniqcharstest1-1.0.dist-info/RECORD
